<?xml version="1.0" encoding="UTF-8" standalone="yes"?>
<tempoReportHaul xmlns:a="http://www.appian.com/ae/types/2009">
    <versionUuid>489e437e-0f11-4690-9256-275c97cff35b</versionUuid>
    <tempoReport a:uuid="c3e37948-623f-430c-98dd-e16bcdeea463" name="Incentives Sales">
        <a:description>Incentives Sales Grid Report for Incentives Site</a:description>
        <a:uiExpr>=#"_a-0000e067-d58d-8000-9ba2-011c48011c48_295492"()</a:uiExpr>
        <a:urlStub>tSfvWg</a:urlStub>
    </tempoReport>
    <roleMap>
        <role name="report_administrator">
            <users/>
            <groups>
                <groupUuid>_e-0000e067-d54a-8000-9aee-01075c01075c_285</groupUuid>
            </groups>
        </role>
        <role name="report_viewer">
            <users/>
            <groups>
                <groupUuid>_e-0000e067-d54a-8000-9aee-01075c01075c_289</groupUuid>
            </groups>
        </role>
    </roleMap>
    <history>
        <historyInfo versionUuid="ccea6c77-db04-4fe9-afd4-6b74d52378c6"/>
        <historyInfo versionUuid="489e437e-0f11-4690-9256-275c97cff35b"/>
    </history>
</tempoReportHaul>
